crossdeploy-0.1.8.dist-info/METADATA
crossdeploy-0.1.8.dist-info/WHEEL
crossdeploy-0.1.8.dist-info/top_level.txt
crossdeploy-0.1.8.dist-info/RECORD
crossdeploy/crossdeploy.cpython-311-x86_64-linux-gnu.so
crossdeploy/version.py
crossdeploy/__init__.py
crossdeploy/imports/__init__.py
crossdeploy/imports/ibmcpd/__init__.py
crossdeploy/imports/ibmcpd/py.typed
crossdeploy/imports/ibmcpd/subscription/__init__.py
crossdeploy/imports/ibmcpd/data_ibmcpd_sp_assets/__init__.py
crossdeploy/imports/ibmcpd/service_provider/__init__.py
crossdeploy/imports/ibmcpd/deployment/__init__.py
crossdeploy/imports/ibmcpd/_jsii/ibmcpd@0.0.0.jsii.tgz
crossdeploy/imports/ibmcpd/_jsii/__init__.py
crossdeploy/imports/ibmcpd/model/__init__.py
crossdeploy/imports/ibmcpd/record/__init__.py
crossdeploy/imports/ibmcpd/provider/__init__.py
crossdeploy/imports/ibmcpd/monitor_instance/__init__.py
crossdeploy/imports/aws/__init__.py
crossdeploy/imports/aws/py.typed
crossdeploy/imports/aws/sagemaker_endpoint_configuration/__init__.py
crossdeploy/imports/aws/data_aws_sagemaker_prebuilt_ecr_image/__init__.py
crossdeploy/imports/aws/sagemaker_model/__init__.py
crossdeploy/imports/aws/sagemaker_endpoint/__init__.py
crossdeploy/imports/aws/_jsii/aws@0.0.0.jsii.tgz
crossdeploy/imports/aws/_jsii/__init__.py
crossdeploy/imports/aws/data_aws_caller_identity/__init__.py
crossdeploy/imports/aws/provider/__init__.py
crossdeploy/cdktf/__init__.py
crossdeploy/cdktf/py.typed
crossdeploy/cdktf/_jsii/cdktf@0.0.0.jsii.tgz
crossdeploy/cdktf/_jsii/__init__.py
crossdeploy/cdktf/testing_matchers/__init__.py
crossdeploy/utils/utils.py
crossdeploy/utils/__init__.py
