Metadata-Version: 2.1
Name: crossdeploy
Version: 0.1.8
Summary: A declarative approach to manage MLOps resources
Home-page: https://github.com/crossdeploy-io/crossdeploy
Author: Randy Phoa
License: MPL 2.0
Classifier: Development Status :: 4 - Beta
Classifier: Intended Audience :: Developers
Classifier: Programming Language :: Python :: 3.9
Requires-Dist: constructs
Requires-Dist: jsii
